{
    "identifier": "5af8980a-97b2-4bae-88b2-1dabe4dc8a3a",
    "slug":"/sopra-steria",
    "type" : "stand",
    "title": "ESN - Sopra",
    "horaires": "Toute la journée",
    "image": "sopra-steria.jpg",
    "content": "Maecenas dictum eros ac urna dictum eleifend. Nullam a nisl purus. Pellentesque lectus tortor, pellentesque eget sollicitudin id, venenatis eu nulla. Etiam finibus lorem neque, at commodo dolor euismod sit amet. Sed a leo malesuada, aliquam nulla a, pulvinar nibh",
    "vcard_id": ""
}