{
    "identifier": "23-craft-work-shop-developpeuses",
    "slug": "metier-developpeuses",
    "type": "craftWorkShop",
    "floor": 3,
    "room": "Tech",
    "organization": "SOPRA",
    "name": "Développeuses",
    "logo": "23-craft-work-shop-developpeuses/devs.jpeg",
    "image": "23-craft-work-shop-developpeuses/devs.jpeg",
    "description": "Emie BOURDEAU et Solenne FOUCAUD de SOPRA STERIA vous partagent leurs parcours professionnels et leurs métiers de Développeuse au quotidien.",
    "slots": "16h45 - 17h30",
    "registrationUrl": "",
    "links": [
        {
            "label": "Site du groupe Covéa",
            "href": "https://www.covea.eu/fr/carrieres"
        },{
            "label": "Lien du site de mon école",
            "href": "https://ensim.univ-lemans.fr/fr/index.html"
        }
    ],
    "documents": [
        {
            "label": "Formulaire d'inscription",
            "href": "none"
        }
    ],
    "speakers": []
}
