{
    "identifier": "32-stand-autres",
    "slug": "stand-pole-emploi-cap-emploi-mission-locale-erip",
    "type": "stand",
    "floor": 0,
    "room": "",
    "organization": "",
    "name": "POLE EMPLOI - CAP EMPLOI - Missions Locales - ERIP",
    "logo": "32-stand-autres/logo.png",
    "image": "32-stand-autres/principale.jpeg",
    "description": "POLE EMPLOI\r\nP\u00F4le emploi est le service public de l\u2019emploi en France. Notre r\u00F4le ? D\u2019une part, indemniser les demandeurs d\u2019emploi et les accompagner vers le retour \u00E0 l\u2019emploi ; et d\u2019autre part, guider les entreprises dans leurs recrutements. C\u2019est la mission que portent nos 54 500 agents, mobilis\u00E9s au quotidien pour anticiper les tendances, innover et f\u00E9d\u00E9rer les acteurs et relais-cl\u00E9s sur le terrain. Et sur notre territoire, P\u00F4le Emploi compte 6 agences, dont 2 \u00E0 Niort.\r\n\r\nCap emploi, des missions au service de l\u2019emploi des personnes handicap\u00E9es : \r\nCAP EMPLOI  accompagne des personnes handicap\u00E9es et des employeurs vers et dans l\u2019emploi. Notre expertise permet d\u2019\u00E9valuer la situation de handicap face \u00E0 l\u2019emploi et d\u2019identifier les moyens de compensation \u00E0 mettre en \u0153uvre tout au long du parcours d\u2019emploi. \r\n\r\n\r\nMISSION LOCALE\r\nC\u2019est une association qui est \u00E0 l\u2019\u00E9coute et au service des jeunes de 16 \u00E0 25 ans qui  propose un accompagnement personnalis\u00E9 portant sur l\u2019orientation, l\u2019insertion professionnelle et sociale. Chaque jeune accueilli b\u00E9n\u00E9ficie de r\u00E9ponses individualis\u00E9es pour r\u00E9ussir son insertion professionnelle et sociale.\r\nLa mission locale compte 18 lieux d\u2019accueil et 3 sites principaux :\r\nMelle\r\nNiort\r\nSt Maixent l\u2019Ecole\r\n\r\nERIP\r\nLes ERIP sont des lieux d'accueil qui proposent un acc\u00E8s simplifi\u00E9 au droit \u00E0 l\u2019information sur la formation, la recherche d\u2019emploi, la validation des acquis de l'exp\u00E9rience (VAE), les m\u00E9tiers, la cr\u00E9ation ou la reprise d\u2019une entreprise\u2026 Les diff\u00E9rentes structures existantes sur les territoires des 3 anciennes r\u00E9gions ont \u00E9t\u00E9 unifi\u00E9es en 2020 en un seul r\u00E9seau r\u00E9gional dot\u00E9 de 42 espaces identifi\u00E9s. \r\n\r\nL\u2019Espace de proximit\u00E9 et ses conseillers vous proposent, en acc\u00E8s libre, toute une gamme de services : entretiens individuels avec ou sans rendez-vous, ateliers th\u00E9matiques, \u00E9v\u00E9nements locaux et ressource documentaire. \r\n\r\nPour qui ?\r\nToute personne, quelque soit son \u00E2ge, scolaris\u00E9e, active (salari\u00E9s, demandeurs d'emploi) ou employeur peut venir rencontrer un conseiller pour un premier niveau d'information.",
    "slots": "10h15 - 17h30",
    "registrationUrl": "",
    "links": [
        {
            "label": "",
            "href": "none"
        }
    ],
    "documents": [
        {
            "label": "Formulaire d'inscription",
            "href": "none"
        }
    ],
    "speakers": []
}
